Metadata-Version: 2.1
Name: x5092json
Version: 1.0.2
Summary: x5092json Utility
Home-page: https://github.com/jcrowgey/x5092json
Author: Joshua Crowgey
Author-email: jcrowgey@uw.edu
License: BSD
Platform: UNKNOWN
Classifier: Development Status :: 5 - Production/Stable
Classifier: Environment :: Console
Classifier: Programming Language :: Python :: 3.5
Classifier: Programming Language :: Python :: 3.6
Classifier: Programming Language :: Python :: 3.7
Requires-Python: >=3.5
